{
  "type" : "FETE_ET_MANIFESTATION",
  "id" : 6251180,
  "nom" : {
    "libelleFr" : "Alpilium : Grou !",
    "libelleEn" : "Alpilium : Grou !",
    "libelleEs" : "Alpilium : Grou !",
    "libelleIt" : "Alpilium : Grou !",
    "libelleDe" : "Alpilium : Grou !",
    "libelleNl" : "Alpilium : Grou !",
    "libelleRu" : "Alpilium : Grou !",
    "libelleZh" : "Alpilium : Grou !",
    "libellePtBR" : "Alpilium : Grou !",
    "libelleJa" : "Alpilium : Grou !"
  },
  "identifier" : "SITRA2_EVE_6251180",
  "state" : "PUBLISHED",
  "gestion" : {
    "dateCreation" : "2022-09-02T13:14:09.872+0000",
    "dateModification" : "2022-09-02T13:18:15.624+0000",
    "dateExportModification" : "2022-11-02T09:07:41.968+0000",
    "membreProprietaire" : {
      "type" : {
        "elementReferenceType" : "MembreSitraType",
        "id" : 233
      },
      "nom" : "Régie Tourisme de la CC Vallée Des Baux-Alpilles",
      "dateCreation" : "2020-09-21T13:49:42.365+0000",
      "dateModification" : "2022-10-24T08:49:50.520+0000",
      "id" : 2081
    },
    "signalerUnProblemeMails" : [ "fontvieille@alpillesenprovence.com", "mouries@alpillesenprovence.com", "web@alpillesenprovence.com" ]
  },
  "informations" : {
    "moyensCommunication" : [ {
      "identifiant" : 77204805,
      "type" : {
        "elementReferenceType" : "MoyenCommunicationType",
        "id" : 201
      },
      "coordonnees" : {
        "fr" : "04 90 92 70 37"
      }
    }, {
      "identifiant" : 102843761,
      "type" : {
        "elementReferenceType" : "MoyenCommunicationType",
        "id" : 201
      },
      "coordonnees" : {
        "fr" : "06 29 19 69 78"
      }
    }, {
      "identifiant" : 77204806,
      "type" : {
        "elementReferenceType" : "MoyenCommunicationType",
        "id" : 204
      },
      "coordonnees" : {
        "fr" : "culture@ville-srdp.fr"
      }
    }, {
      "identifiant" : 102843848,
      "type" : {
        "elementReferenceType" : "MoyenCommunicationType",
        "id" : 205
      },
      "coordonnees" : {
        "fr" : "https://www.mairie-saintremydeprovence.com/que-faire-a-saint-remy/envie-de-culture/alpilium/"
      }
    }, {
      "identifiant" : 102843867,
      "type" : {
        "elementReferenceType" : "MoyenCommunicationType",
        "id" : 207
      },
      "coordonnees" : {
        "fr" : "https://www.facebook.com/alpiliumsaisonculturelle"
      }
    } ],
    "structureGestion" : {
      "type" : "STRUCTURE",
      "id" : 5482390
    }
  },
  "presentation" : {
    "descriptifCourt" : {
      "libelleFr" : "Pièce de théâtre, \"Grou !\", le jeudi 10 novembre à 18h30 à l'Alpilium !",
      "libelleEn" : "Theatre play, \"Grou!\", on Thursday 10 November at 18:30 at the Alpilium!",
      "libelleDe" : "Theaterstück, \"Grou!\", am Donnerstag, den 10. November um 18.30 Uhr im Alpilium!"
    },
    "descriptifDetaille" : {
      "libelleFr" : "Un extraordinaire voyage à remonter le temps, parsemé d’inventions géniales de toutes sortes et bourré d’inventivité. Un régal pour toutes les générations…\r\n\r\nLa nuit de ses 12 ans, Charles se faufile dans la cuisine et pense très fort à un vœu avant de souffler ses bougies : il veut grandir plus vite… C’est ainsi que grou, homme de Cro-Magnon, surgit inopinément du four, habillé en peau de bête et muni d’une torche enflammée. Malgré les premières difficultés de communication, grou va permettre à Charles de lui faire traverser les âges…\r\n\r\n« Truffé d’effets spéciaux, de rebondissements, mais aussi de bons sentiments, Grou !, bien bluffant, multiplie les prises de risques physiques et tient le spectateur en haleine du début à la fin. (…) Si, après cela, il est des enfants qui s’ennuient encore au théâtre, nous rendons notre tablier. » La Libre Belgique\r\n\r\nCe spectacle a reçu le Prix de la Ministre de l’Enseignement Fondamental aux Rencontres de théâtre Jeune Public de Huy 2018.\r\n\r\nThéâtre en famille\r\nCie Renards / Effet Mer\r\nTarif C\r\nÉcriture : Baptiste Toulemonde\r\nMise en scène : Arthur oudar et Baptiste Toulemonde\r\nJeu : Adrien Letartre, Baptiste Toulemonde\r\nRegard extérieur : Hugo giordano\r\nScénographie : Bertrand nodet\r\nCréation lumières : Amélie géhin\r\nCréation sonore : guillaume Vesin\r\nRégie : Candice Hansel\r\nDurée : 1h\r\nSpectacle conseillé à partir de 7 ans"
    }
  },
  "localisation" : {
    "adresse" : {
      "nomDuLieu" : "Alpilium",
      "adresse1" : "Avenue Marechal De Lattre de Tassigny",
      "codePostal" : "13210",
      "commune" : {
        "id" : 4511
      }
    },
    "geolocalisation" : {
      "valide" : true,
      "geoJson" : {
        "type" : "Point",
        "coordinates" : [ 4.842372, 43.793094 ]
      }
    },
    "perimetreGeographique" : [ {
      "id" : 4511
    } ]
  },
  "liens" : {
    "liensObjetsTouristiquesTypes" : [ {
      "type" : "DEFAUT",
      "libelleFr" : "En lien avec",
      "libelleEn" : "Related to",
      "libelleEs" : "En relación con",
      "libelleIt" : "In collegamento con",
      "libelleDe" : "In Verbindung mit",
      "libelleNl" : "In verband met",
      "libelleRu" : "Применительно к",
      "libelleZh" : "与携手",
      "libellePtBR" : "Em relação com",
      "libelleJa" : "と関連して",
      "objetTouristique" : {
        "type" : "EQUIPEMENT",
        "id" : 5523560
      }
    }, {
      "type" : "DEFAUT",
      "libelleFr" : "En lien avec",
      "libelleEn" : "Related to",
      "libelleEs" : "En relación con",
      "libelleIt" : "In collegamento con",
      "libelleDe" : "In Verbindung mit",
      "libelleNl" : "In verband met",
      "libelleRu" : "Применительно к",
      "libelleZh" : "与携手",
      "libellePtBR" : "Em relação com",
      "libelleJa" : "と関連して",
      "objetTouristique" : {
        "type" : "FETE_ET_MANIFESTATION",
        "id" : 6251196
      }
    }, {
      "type" : "DEFAUT",
      "libelleFr" : "En lien avec",
      "libelleEn" : "Related to",
      "libelleEs" : "En relación con",
      "libelleIt" : "In collegamento con",
      "libelleDe" : "In Verbindung mit",
      "libelleNl" : "In verband met",
      "libelleRu" : "Применительно к",
      "libelleZh" : "与携手",
      "libellePtBR" : "Em relação com",
      "libelleJa" : "と関連して",
      "objetTouristique" : {
        "type" : "FETE_ET_MANIFESTATION",
        "id" : 6251223
      }
    }, {
      "type" : "DEFAUT",
      "libelleFr" : "En lien avec",
      "libelleEn" : "Related to",
      "libelleEs" : "En relación con",
      "libelleIt" : "In collegamento con",
      "libelleDe" : "In Verbindung mit",
      "libelleNl" : "In verband met",
      "libelleRu" : "Применительно к",
      "libelleZh" : "与携手",
      "libellePtBR" : "Em relação com",
      "libelleJa" : "と関連して",
      "objetTouristique" : {
        "type" : "FETE_ET_MANIFESTATION",
        "id" : 6251246
      }
    }, {
      "type" : "DEFAUT",
      "libelleFr" : "En lien avec",
      "libelleEn" : "Related to",
      "libelleEs" : "En relación con",
      "libelleIt" : "In collegamento con",
      "libelleDe" : "In Verbindung mit",
      "libelleNl" : "In verband met",
      "libelleRu" : "Применительно к",
      "libelleZh" : "与携手",
      "libellePtBR" : "Em relação com",
      "libelleJa" : "と関連して",
      "objetTouristique" : {
        "type" : "FETE_ET_MANIFESTATION",
        "id" : 6251266
      }
    }, {
      "type" : "DEFAUT",
      "libelleFr" : "En lien avec",
      "libelleEn" : "Related to",
      "libelleEs" : "En relación con",
      "libelleIt" : "In collegamento con",
      "libelleDe" : "In Verbindung mit",
      "libelleNl" : "In verband met",
      "libelleRu" : "Применительно к",
      "libelleZh" : "与携手",
      "libellePtBR" : "Em relação com",
      "libelleJa" : "と関連して",
      "objetTouristique" : {
        "type" : "FETE_ET_MANIFESTATION",
        "id" : 6251285
      }
    }, {
      "type" : "DEFAUT",
      "libelleFr" : "En lien avec",
      "libelleEn" : "Related to",
      "libelleEs" : "En relación con",
      "libelleIt" : "In collegamento con",
      "libelleDe" : "In Verbindung mit",
      "libelleNl" : "In verband met",
      "libelleRu" : "Применительно к",
      "libelleZh" : "与携手",
      "libellePtBR" : "Em relação com",
      "libelleJa" : "と関連して",
      "objetTouristique" : {
        "type" : "FETE_ET_MANIFESTATION",
        "id" : 6251299
      }
    }, {
      "type" : "DEFAUT",
      "libelleFr" : "En lien avec",
      "libelleEn" : "Related to",
      "libelleEs" : "En relación con",
      "libelleIt" : "In collegamento con",
      "libelleDe" : "In Verbindung mit",
      "libelleNl" : "In verband met",
      "libelleRu" : "Применительно к",
      "libelleZh" : "与携手",
      "libellePtBR" : "Em relação com",
      "libelleJa" : "と関連して",
      "objetTouristique" : {
        "type" : "FETE_ET_MANIFESTATION",
        "id" : 6251310
      }
    }, {
      "type" : "DEFAUT",
      "libelleFr" : "En lien avec",
      "libelleEn" : "Related to",
      "libelleEs" : "En relación con",
      "libelleIt" : "In collegamento con",
      "libelleDe" : "In Verbindung mit",
      "libelleNl" : "In verband met",
      "libelleRu" : "Применительно к",
      "libelleZh" : "与携手",
      "libellePtBR" : "Em relação com",
      "libelleJa" : "と関連して",
      "objetTouristique" : {
        "type" : "FETE_ET_MANIFESTATION",
        "id" : 6251325
      }
    }, {
      "type" : "DEFAUT",
      "libelleFr" : "En lien avec",
      "libelleEn" : "Related to",
      "libelleEs" : "En relación con",
      "libelleIt" : "In collegamento con",
      "libelleDe" : "In Verbindung mit",
      "libelleNl" : "In verband met",
      "libelleRu" : "Применительно к",
      "libelleZh" : "与携手",
      "libellePtBR" : "Em relação com",
      "libelleJa" : "と関連して",
      "objetTouristique" : {
        "type" : "FETE_ET_MANIFESTATION",
        "id" : 6251352
      }
    }, {
      "type" : "DEFAUT",
      "libelleFr" : "En lien avec",
      "libelleEn" : "Related to",
      "libelleEs" : "En relación con",
      "libelleIt" : "In collegamento con",
      "libelleDe" : "In Verbindung mit",
      "libelleNl" : "In verband met",
      "libelleRu" : "Применительно к",
      "libelleZh" : "与携手",
      "libellePtBR" : "Em relação com",
      "libelleJa" : "と関連して",
      "objetTouristique" : {
        "type" : "FETE_ET_MANIFESTATION",
        "id" : 6251358
      }
    }, {
      "type" : "DEFAUT",
      "libelleFr" : "En lien avec",
      "libelleEn" : "Related to",
      "libelleEs" : "En relación con",
      "libelleIt" : "In collegamento con",
      "libelleDe" : "In Verbindung mit",
      "libelleNl" : "In verband met",
      "libelleRu" : "Применительно к",
      "libelleZh" : "与携手",
      "libellePtBR" : "Em relação com",
      "libelleJa" : "と関連して",
      "objetTouristique" : {
        "type" : "FETE_ET_MANIFESTATION",
        "id" : 6251367
      }
    }, {
      "type" : "DEFAUT",
      "libelleFr" : "En lien avec",
      "libelleEn" : "Related to",
      "libelleEs" : "En relación con",
      "libelleIt" : "In collegamento con",
      "libelleDe" : "In Verbindung mit",
      "libelleNl" : "In verband met",
      "libelleRu" : "Применительно к",
      "libelleZh" : "与携手",
      "libellePtBR" : "Em relação com",
      "libelleJa" : "と関連して",
      "objetTouristique" : {
        "type" : "FETE_ET_MANIFESTATION",
        "id" : 6251391
      }
    } ]
  },
  "prestations" : {
    "animauxAcceptes" : "NON_ACCEPTES",
    "animauxAcceptesSupplement" : "NON_DISPONIBLE",
    "languesParlees" : [ {
      "elementReferenceType" : "Langue",
      "id" : 1197
    } ],
    "ageMin" : 84,
    "uniteAgeMin" : "ANNEE"
  },
  "ouverture" : {
    "periodeEnClair" : {
      "libelleFr" : "Jeudi 10 novembre 2022 à 18h30.",
      "libelleEn" : "Thursday 10 November 2022 at 6.30 pm.",
      "libelleEs" : "Jueves, 10 de noviembre de 2022 a 18:30.",
      "libelleIt" : "Giovedì 10 novembre 2022 alle 18:30.",
      "libelleDe" : "Donnerstag, den 10. November 2022 um 18.30 Uhr.",
      "libelleNl" : "Donderdag 10 november 2022 om 18.30 u.",
      "libelleRu" : "Четверг 10 ноября 2022  до 18h30.",
      "libelleZh" : "2022年11月10日, 星期四   在 小时小时分钟.",
      "libellePtBR" : "Quinta-feira 10 Novembro 2022 para  18h30.",
      "libelleJa" : "木曜日 10 11月 2022 6.30 午後 に."
    },
    "periodeEnClairGenerationMode" : "AUTOMATIQUE",
    "indicationsPeriode" : [ {
      "elementReferenceType" : "IndicationPeriode",
      "id" : 416
    } ],
    "periodesOuvertures" : [ {
      "identifiant" : 24214367,
      "dateDebut" : "2022-11-10",
      "dateFin" : "2022-11-10",
      "horaireOuverture" : "18:30:00",
      "type" : "OUVERTURE_TOUS_LES_JOURS",
      "tousLesAns" : false,
      "identifiantTechnique" : 24214367
    } ]
  },
  "descriptionTarif" : {
    "indicationTarif" : "PAYANT",
    "gratuit" : false,
    "tarifsEnClair" : {
      "libelleFr" : "Tarif C\r\n• Plein tarif : 14€\r\n• Abonné et accompagnateur famille (sur présentation de la carte) : 10€\r\n• Groupe (à partir de 10 personnes) : 8€\r\n• Réduit (-26ans, demandeurs d'emploi, bénéficiaires des minimas sociaux, sur présentation d'un justificatif)  : 6€."
    },
    "tarifsEnClairGenerationMode" : "AUTOMATIQUE",
    "complement" : {
      "libelleFr" : "Tarif C\r\n• Plein tarif : 14€\r\n• Abonné et accompagnateur famille (sur présentation de la carte) : 10€\r\n• Groupe (à partir de 10 personnes) : 8€\r\n• Réduit (-26ans, demandeurs d'emploi, bénéficiaires des minimas sociaux, sur présentation d'un justificatif)  : 6€"
    },
    "modesPaiement" : [ {
      "elementReferenceType" : "ModePaiement",
      "id" : 1268
    }, {
      "elementReferenceType" : "ModePaiement",
      "id" : 1271
    }, {
      "elementReferenceType" : "ModePaiement",
      "id" : 1277
    } ],
    "devise" : "EUR",
    "conditions" : { }
  },
  "reservation" : {
    "organismes" : [ {
      "identifiant" : 6758940,
      "structureReference" : {
        "type" : "STRUCTURE",
        "id" : 5482390
      },
      "nom" : "Alpilium",
      "type" : {
        "elementReferenceType" : "ReservationType",
        "id" : 475
      },
      "moyensCommunication" : [ {
        "identifiant" : 77204805,
        "type" : {
          "elementReferenceType" : "MoyenCommunicationType",
          "id" : 201
        },
        "coordonnees" : {
          "fr" : "04 90 92 70 37"
        }
      }, {
        "identifiant" : 102843761,
        "type" : {
          "elementReferenceType" : "MoyenCommunicationType",
          "id" : 201
        },
        "coordonnees" : {
          "fr" : "06 29 19 69 78"
        }
      }, {
        "identifiant" : 77204806,
        "type" : {
          "elementReferenceType" : "MoyenCommunicationType",
          "id" : 204
        },
        "coordonnees" : {
          "fr" : "culture@ville-srdp.fr"
        }
      }, {
        "identifiant" : 102843867,
        "type" : {
          "elementReferenceType" : "MoyenCommunicationType",
          "id" : 207
        },
        "coordonnees" : {
          "fr" : "https://www.facebook.com/alpiliumsaisonculturelle"
        }
      } ],
      "locked" : false
    } ]
  },
  "criteresInternes" : [ {
    "id" : 18428
  } ],
  "illustrations" : [ {
    "identifiant" : 13929810,
    "link" : false,
    "type" : "IMAGE",
    "nom" : {
      "libelleFr" : "Pièce de théatre en famille, \"Grou\" à l'Alpilium"
    },
    "copyright" : {
      "libelleFr" : "Alpilium"
    },
    "traductionFichiers" : [ {
      "locale" : "fr",
      "url" : "https://static.apidae-tourisme.com/filestore/objets-touristiques/images/137/155/14195593.jpg",
      "urlListe" : "https://static.apidae-tourisme.com/filestore/objets-touristiques/images/137/155/14195593-liste.jpg",
      "urlFiche" : "https://static.apidae-tourisme.com/filestore/objets-touristiques/images/137/155/14195593-fiche.jpg",
      "urlDiaporama" : "https://static.apidae-tourisme.com/filestore/objets-touristiques/images/137/155/14195593-diaporama.jpg",
      "extension" : "jpg",
      "fileName" : "Grou",
      "taille" : 62079,
      "hauteur" : 570,
      "largeur" : 1555,
      "lastModifiedDate" : "2022-09-02T13:18:17.002+0000"
    } ],
    "locked" : false
  }, {
    "identifiant" : 13929811,
    "link" : false,
    "type" : "IMAGE",
    "nom" : {
      "libelleFr" : "Pièce de théatre en famille, \"Grou\" à l'Alpilium"
    },
    "copyright" : {
      "libelleFr" : "Alpilium"
    },
    "traductionFichiers" : [ {
      "locale" : "fr",
      "url" : "https://static.apidae-tourisme.com/filestore/objets-touristiques/images/138/155/14195594.jpg",
      "urlListe" : "https://static.apidae-tourisme.com/filestore/objets-touristiques/images/138/155/14195594-liste.jpg",
      "urlFiche" : "https://static.apidae-tourisme.com/filestore/objets-touristiques/images/138/155/14195594-fiche.jpg",
      "urlDiaporama" : "https://static.apidae-tourisme.com/filestore/objets-touristiques/images/138/155/14195594-diaporama.jpg",
      "extension" : "jpg",
      "fileName" : "Grou_10_novembre_2022",
      "taille" : 224460,
      "hauteur" : 1200,
      "largeur" : 848,
      "lastModifiedDate" : "2022-09-02T13:18:15.740+0000"
    } ],
    "locked" : false
  }, {
    "identifiant" : 13929812,
    "link" : false,
    "type" : "IMAGE",
    "nom" : {
      "libelleFr" : "Pièce de théatre en famille, \"Grou\" à l'Alpilium"
    },
    "copyright" : {
      "libelleFr" : "Alpilium"
    },
    "traductionFichiers" : [ {
      "locale" : "fr",
      "url" : "https://static.apidae-tourisme.com/filestore/objets-touristiques/images/139/155/14195595.jpg",
      "urlListe" : "https://static.apidae-tourisme.com/filestore/objets-touristiques/images/139/155/14195595-liste.jpg",
      "urlFiche" : "https://static.apidae-tourisme.com/filestore/objets-touristiques/images/139/155/14195595-fiche.jpg",
      "urlDiaporama" : "https://static.apidae-tourisme.com/filestore/objets-touristiques/images/139/155/14195595-diaporama.jpg",
      "extension" : "jpg",
      "fileName" : "Grou_Alpilium_prog-Saison-Culturelle-2022-2023",
      "taille" : 575308,
      "hauteur" : 1241,
      "largeur" : 768,
      "lastModifiedDate" : "2022-09-02T13:18:16.117+0000"
    } ],
    "locked" : false
  }, {
    "identifiant" : 13929782,
    "link" : false,
    "type" : "IMAGE",
    "nom" : {
      "libelleFr" : "Tarifs des spectacles de l'Alpilium"
    },
    "legende" : {
      "libelleFr" : "Spectacle \"Focus Danse\" à l'Alpilium"
    },
    "copyright" : {
      "libelleFr" : "Alpilium"
    },
    "traductionFichiers" : [ {
      "locale" : "fr",
      "url" : "https://static.apidae-tourisme.com/filestore/objets-touristiques/images/106/155/14195562.jpg",
      "urlListe" : "https://static.apidae-tourisme.com/filestore/objets-touristiques/images/106/155/14195562-liste.jpg",
      "urlFiche" : "https://static.apidae-tourisme.com/filestore/objets-touristiques/images/106/155/14195562-fiche.jpg",
      "urlDiaporama" : "https://static.apidae-tourisme.com/filestore/objets-touristiques/images/106/155/14195562-diaporama.jpg",
      "extension" : "jpg",
      "fileName" : "Alpilium_prog-Saison-Culturelle-2022-2023_page-0029_Tarifs",
      "taille" : 583480,
      "hauteur" : 1241,
      "largeur" : 768,
      "lastModifiedDate" : "2022-09-02T13:18:16.568+0000"
    } ],
    "locked" : false
  } ],
  "multimedias" : [ {
    "identifiant" : 13929783,
    "link" : true,
    "type" : "INSTAGRAM",
    "copyright" : {
      "libelleFr" : "Alpilium"
    },
    "traductionFichiers" : [ {
      "locale" : "fr",
      "url" : "https://www.instagram.com/alpilium_saisonculturelle/"
    }, {
      "locale" : "en",
      "url" : "https://www.instagram.com/alpilium_saisonculturelle/"
    }, {
      "locale" : "de",
      "url" : "https://www.instagram.com/alpilium_saisonculturelle/"
    } ],
    "locked" : false
  } ],
  "territoires" : [ {
    "type" : "TERRITOIRE",
    "id" : 591381
  }, {
    "type" : "TERRITOIRE",
    "id" : 591419
  }, {
    "type" : "TERRITOIRE",
    "id" : 658199
  }, {
    "type" : "TERRITOIRE",
    "id" : 4819487
  }, {
    "type" : "TERRITOIRE",
    "id" : 4881511
  }, {
    "type" : "TERRITOIRE",
    "id" : 5127066
  }, {
    "type" : "TERRITOIRE",
    "id" : 5427354
  }, {
    "type" : "TERRITOIRE",
    "id" : 5447176
  }, {
    "type" : "TERRITOIRE",
    "id" : 5447185
  } ],
  "datesOuverture" : [ "2022-11-10" ],
  "informationsFeteEtManifestation" : {
    "typesManifestation" : [ {
      "elementReferenceType" : "FeteEtManifestationType",
      "id" : 1958
    } ],
    "categories" : [ {
      "elementReferenceType" : "FeteEtManifestationCategorie",
      "id" : 2134
    } ],
    "portee" : {
      "elementReferenceType" : "FeteEtManifestationPortee",
      "id" : 2351
    },
    "nomLieu" : "Alpilium"
  },
  "formatVersion" : "v002",
  "expiration" : {
    "dateExpiration" : "2022-11-10T00:00:00.000+0000",
    "expirationAction" : "SUPPRIMER"
  },
  "enquete" : { }
}