{
  "type" : "STRUCTURE",
  "id" : 5223237,
  "nom" : {
    "libelleFr" : "Musée Regards de Provence",
    "libelleEn" : "Fondation Regards de Provence",
    "libelleEs" : "Fondation Regards de Provence",
    "libelleIt" : "Fondation Regards de Provence",
    "libelleDe" : "Fondation Regards de Provence",
    "libelleNl" : "Fondation Regards de Provence"
  },
  "identifier" : "SITRA2_STR_5223237",
  "state" : "PUBLISHED",
  "gestion" : {
    "dateCreation" : "2019-04-01T11:56:59.424+0000",
    "dateModification" : "2022-08-30T11:56:35.424+0000",
    "dateExportModification" : "2022-08-30T11:57:03.642+0000",
    "membreProprietaire" : {
      "type" : {
        "elementReferenceType" : "MembreSitraType",
        "id" : 233
      },
      "nom" : "Office Métropolitain de tourisme et des congrès de Marseille",
      "dateCreation" : "2017-02-13T09:29:30.842+0000",
      "dateModification" : "2022-10-24T08:49:48.642+0000",
      "id" : 1490,
      "siteWeb" : "http://www.marseille-tourisme.com"
    },
    "signalerUnProblemeMails" : [ "alegrand@marseille-tourisme.com", "hcochet@marseille-tourisme.com", "jorengo@marseille-tourisme.com", "lchavet@marseille-tourisme.com", "mamadier@marseille-tourisme.com", "sbenimeli@marseille-tourisme.com" ]
  },
  "informations" : {
    "moyensCommunication" : [ {
      "identifiant" : 70513108,
      "type" : {
        "elementReferenceType" : "MoyenCommunicationType",
        "id" : 201
      },
      "coordonnees" : {
        "fr" : "04 96 17 40 40"
      }
    }, {
      "identifiant" : 70513109,
      "type" : {
        "elementReferenceType" : "MoyenCommunicationType",
        "id" : 201
      },
      "coordonnees" : {
        "fr" : "04 91 04 68 15"
      }
    }, {
      "identifiant" : 70513110,
      "type" : {
        "elementReferenceType" : "MoyenCommunicationType",
        "id" : 201
      },
      "coordonnees" : {
        "fr" : "04 91 04 68 32"
      }
    }, {
      "identifiant" : 70513111,
      "type" : {
        "elementReferenceType" : "MoyenCommunicationType",
        "id" : 204
      },
      "coordonnees" : {
        "fr" : "adeline.granerau@museeregardsdeprovence.com"
      }
    }, {
      "identifiant" : 70513112,
      "type" : {
        "elementReferenceType" : "MoyenCommunicationType",
        "id" : 205
      },
      "coordonnees" : {
        "fr" : "http://www.museeregardsdeprovence.com/"
      }
    } ],
    "informationsLegales" : {
      "siret" : "42020008100016",
      "codeApeNaf" : "913E",
      "modeGestion" : {
        "elementReferenceType" : "ModeGestion",
        "id" : 133
      }
    }
  },
  "localisation" : {
    "adresse" : {
      "adresse1" : "Allées Regards de Provence",
      "adresse2" : "Avenue Vaudoyer",
      "codePostal" : "13002",
      "bureauDistribution" : "MARSEILLE",
      "commune" : {
        "id" : 4532
      }
    },
    "geolocalisation" : {
      "valide" : true,
      "geoJson" : {
        "type" : "Point",
        "coordinates" : [ 5.363390, 43.297426 ]
      }
    },
    "perimetreGeographique" : [ {
      "id" : 4532
    } ]
  },
  "descriptionTarif" : {
    "tarifsEnClairGenerationMode" : "MANUEL",
    "devise" : "EUR",
    "conditions" : { }
  },
  "reservation" : { },
  "contacts" : [ {
    "identifiant" : 21140779,
    "referent" : true,
    "civilite" : {
      "elementReferenceType" : "ContactCivilite",
      "id" : 442
    },
    "nom" : "DUMON",
    "prenom" : "Adeline",
    "fonction" : {
      "elementReferenceType" : "ContactFonction",
      "id" : 458
    },
    "moyensCommunication" : [ {
      "identifiant" : 101889572,
      "type" : {
        "elementReferenceType" : "MoyenCommunicationType",
        "id" : 204
      },
      "coordonnees" : {
        "fr" : "adeline.dumon@museeregardsdeprovence.com"
      }
    }, {
      "identifiant" : 101889585,
      "type" : {
        "elementReferenceType" : "MoyenCommunicationType",
        "id" : 201
      },
      "coordonnees" : {
        "fr" : "04 96 17 40 40"
      }
    } ]
  }, {
    "identifiant" : 21140766,
    "referent" : false,
    "civilite" : {
      "elementReferenceType" : "ContactCivilite",
      "id" : 442
    },
    "nom" : "DAUDIN",
    "prenom" : "Marie-France",
    "titre" : {
      "libelleFr" : "Responsable commerciale et événementiel"
    },
    "fonction" : {
      "elementReferenceType" : "ContactFonction",
      "id" : 463
    },
    "moyensCommunication" : [ {
      "identifiant" : 101889493,
      "type" : {
        "elementReferenceType" : "MoyenCommunicationType",
        "id" : 201
      },
      "coordonnees" : {
        "fr" : "04 96 17 40 41"
      }
    }, {
      "identifiant" : 101889494,
      "type" : {
        "elementReferenceType" : "MoyenCommunicationType",
        "id" : 204
      },
      "coordonnees" : {
        "fr" : "resa@museeregardsdeprovence.com"
      }
    } ]
  }, {
    "identifiant" : 21140773,
    "referent" : false,
    "civilite" : {
      "elementReferenceType" : "ContactCivilite",
      "id" : 443
    },
    "nom" : "DUMON",
    "prenom" : "Pierre",
    "fonction" : {
      "elementReferenceType" : "ContactFonction",
      "id" : 458
    },
    "moyensCommunication" : [ {
      "identifiant" : 101889544,
      "type" : {
        "elementReferenceType" : "MoyenCommunicationType",
        "id" : 201
      },
      "coordonnees" : {
        "fr" : "04 91 04 68 15"
      }
    } ]
  } ],
  "territoires" : [ {
    "type" : "TERRITOIRE",
    "id" : 591381
  }, {
    "type" : "TERRITOIRE",
    "id" : 591419
  }, {
    "type" : "TERRITOIRE",
    "id" : 5127066
  }, {
    "type" : "TERRITOIRE",
    "id" : 5427637
  }, {
    "type" : "TERRITOIRE",
    "id" : 5460436
  }, {
    "type" : "TERRITOIRE",
    "id" : 5693878
  }, {
    "type" : "TERRITOIRE",
    "id" : 5693903
  }, {
    "type" : "TERRITOIRE",
    "id" : 6008197
  } ],
  "informationsStructure" : { },
  "formatVersion" : "v002",
  "enquete" : { }
}