{
  "type" : "STRUCTURE",
  "id" : 5550805,
  "nom" : {
    "libelleFr" : "La Belle Échappée",
    "libelleEn" : "La Belle Échappée",
    "libelleIt" : "La Belle Échappée",
    "libelleDe" : "La Belle Échappée",
    "libelleNl" : "La Belle Échappée"
  },
  "identifier" : "SITRA2_STR_5550805",
  "state" : "PUBLISHED",
  "gestion" : {
    "dateCreation" : "2020-06-09T04:23:53.197+0000",
    "dateModification" : "2022-05-31T13:56:50.454+0000",
    "dateExportModification" : "2022-10-04T14:00:22.552+0000",
    "membreProprietaire" : {
      "type" : {
        "elementReferenceType" : "MembreSitraType",
        "id" : 233
      },
      "nom" : "Office de Tourisme d'Aix en Provence",
      "dateCreation" : "2020-02-14T10:34:37.912+0000",
      "dateModification" : "2022-10-24T08:49:34.452+0000",
      "id" : 1988,
      "siteWeb" : "http://www.aixenprovencetourism.com"
    },
    "signalerUnProblemeMails" : [ "jchevalier@aixenprovencetourism.com", "sdardenne@aixenprovencetourism.com", "vmontpellaz@aixenprovencetourism.com" ]
  },
  "informations" : {
    "moyensCommunication" : [ {
      "identifiant" : 80021021,
      "type" : {
        "elementReferenceType" : "MoyenCommunicationType",
        "id" : 201
      },
      "coordonnees" : {
        "fr" : "06 51 41 83 21"
      }
    }, {
      "identifiant" : 80021022,
      "type" : {
        "elementReferenceType" : "MoyenCommunicationType",
        "id" : 204
      },
      "coordonnees" : {
        "fr" : "contact@labelleechappee.fr"
      }
    }, {
      "identifiant" : 80021023,
      "type" : {
        "elementReferenceType" : "MoyenCommunicationType",
        "id" : 205
      },
      "coordonnees" : {
        "fr" : "http://labelleechappee.fr"
      }
    } ],
    "informationsLegales" : { }
  },
  "localisation" : {
    "adresse" : {
      "codePostal" : "13100",
      "commune" : {
        "id" : 4412
      }
    },
    "geolocalisation" : {
      "valide" : true,
      "geoJson" : {
        "type" : "Point",
        "coordinates" : [ 5.445328, 43.526528 ]
      }
    },
    "perimetreGeographique" : [ {
      "id" : 4412
    } ]
  },
  "descriptionTarif" : {
    "tarifsEnClairGenerationMode" : "MANUEL",
    "devise" : "EUR",
    "conditions" : { }
  },
  "reservation" : { },
  "contacts" : [ {
    "identifiant" : 18705517,
    "referent" : true,
    "civilite" : {
      "elementReferenceType" : "ContactCivilite",
      "id" : 443
    },
    "nom" : "Cloysil",
    "prenom" : "Eric",
    "fonction" : {
      "elementReferenceType" : "ContactFonction",
      "id" : 458
    },
    "moyensCommunication" : [ {
      "identifiant" : 99816225,
      "type" : {
        "elementReferenceType" : "MoyenCommunicationType",
        "id" : 201
      },
      "coordonnees" : {
        "fr" : "06 51 41 83 21"
      }
    }, {
      "identifiant" : 99816231,
      "type" : {
        "elementReferenceType" : "MoyenCommunicationType",
        "id" : 204
      },
      "coordonnees" : {
        "fr" : "contact@labelleechappee.fr"
      }
    } ]
  } ],
  "territoires" : [ {
    "type" : "TERRITOIRE",
    "id" : 591381
  }, {
    "type" : "TERRITOIRE",
    "id" : 591419
  }, {
    "type" : "TERRITOIRE",
    "id" : 5127066
  }, {
    "type" : "TERRITOIRE",
    "id" : 5427620
  }, {
    "type" : "TERRITOIRE",
    "id" : 5427637
  }, {
    "type" : "TERRITOIRE",
    "id" : 5460325
  }, {
    "type" : "TERRITOIRE",
    "id" : 5693839
  }, {
    "type" : "TERRITOIRE",
    "id" : 5775948
  }, {
    "type" : "TERRITOIRE",
    "id" : 5853930
  } ],
  "informationsStructure" : { },
  "formatVersion" : "v002",
  "enquete" : { }
}