{
  "type" : "STRUCTURE",
  "id" : 5225399,
  "nom" : {
    "libelleFr" : "Mairie de Maillane",
    "libelleEn" : "Hôtel de ville",
    "libelleIt" : "Hôtel de ville",
    "libelleDe" : "Hôtel de ville",
    "libelleNl" : "Hôtel de ville"
  },
  "identifier" : "SITRA2_STR_5225399",
  "state" : "PUBLISHED",
  "gestion" : {
    "dateCreation" : "2019-04-01T12:54:12.150+0000",
    "dateModification" : "2021-11-10T14:44:37.728+0000",
    "dateExportModification" : "2022-09-01T13:31:09.987+0000",
    "membreProprietaire" : {
      "type" : {
        "elementReferenceType" : "MembreSitraType",
        "id" : 233
      },
      "nom" : "Office de Tourisme Intercommunal de Terre de Provence",
      "dateCreation" : "2020-10-28T10:42:53.102+0000",
      "dateModification" : "2022-10-24T08:49:48.093+0000",
      "id" : 2119
    },
    "signalerUnProblemeMails" : [ "accueil.oti@terredeprovence-agglo.com", "accueil2.oti@terredeprovence-agglo.com", "espaceculturetourisme@orange.fr", "office.tourisme@st-andiol.fr", "office.tourisme@ville-graveson.fr", "ot-culture@maillane.fr", "promotion.oti@terredeprovence-agglo.com", "romain.pascal@ville-graveson.fr", "tourisme@noves.fr", "tourisme@terredeprovence-agglo.com" ]
  },
  "informations" : {
    "moyensCommunication" : [ {
      "identifiant" : 70519668,
      "type" : {
        "elementReferenceType" : "MoyenCommunicationType",
        "id" : 201
      },
      "coordonnees" : {
        "fr" : "04 90 95 74 06"
      },
      "observation" : {
        "libelleFr" : "Mairie de Maillane"
      }
    }, {
      "identifiant" : 93167291,
      "type" : {
        "elementReferenceType" : "MoyenCommunicationType",
        "id" : 202
      },
      "coordonnees" : {
        "fr" : "04 90 90 52 84"
      }
    }, {
      "identifiant" : 93167290,
      "type" : {
        "elementReferenceType" : "MoyenCommunicationType",
        "id" : 204
      },
      "coordonnees" : {
        "fr" : "accueil@mairiemaillane.fr"
      }
    }, {
      "identifiant" : 70519672,
      "type" : {
        "elementReferenceType" : "MoyenCommunicationType",
        "id" : 205
      },
      "coordonnees" : {
        "fr" : "http://www.mairiemaillane.fr/"
      }
    } ],
    "informationsLegales" : {
      "modeGestion" : {
        "elementReferenceType" : "ModeGestion",
        "id" : 134
      }
    }
  },
  "localisation" : {
    "adresse" : {
      "adresse1" : "Place de l'église",
      "codePostal" : "13910",
      "commune" : {
        "id" : 4463
      }
    },
    "geolocalisation" : {
      "valide" : true,
      "geoJson" : {
        "type" : "Point",
        "coordinates" : [ 4.782184, 43.832109 ]
      }
    },
    "perimetreGeographique" : [ {
      "id" : 4463
    } ]
  },
  "descriptionTarif" : {
    "tarifsEnClairGenerationMode" : "MANUEL",
    "devise" : "EUR",
    "conditions" : { }
  },
  "reservation" : { },
  "contacts" : [ {
    "identifiant" : 18776232,
    "referent" : true,
    "titre" : {
      "libelleFr" : "Mairie Maillane"
    },
    "fonction" : {
      "elementReferenceType" : "ContactFonction",
      "id" : 470
    },
    "moyensCommunication" : [ {
      "identifiant" : 93587548,
      "type" : {
        "elementReferenceType" : "MoyenCommunicationType",
        "id" : 201
      },
      "coordonnees" : {
        "fr" : "04 90 95 74 06"
      }
    }, {
      "identifiant" : 93587555,
      "type" : {
        "elementReferenceType" : "MoyenCommunicationType",
        "id" : 204
      },
      "coordonnees" : {
        "fr" : "accueil@mairiemaillane.fr"
      }
    } ]
  }, {
    "identifiant" : 18781727,
    "referent" : false,
    "titre" : {
      "libelleFr" : "OT Maillane"
    },
    "fonction" : {
      "elementReferenceType" : "ContactFonction",
      "id" : 459
    },
    "moyensCommunication" : [ {
      "identifiant" : 93587588,
      "type" : {
        "elementReferenceType" : "MoyenCommunicationType",
        "id" : 201
      },
      "coordonnees" : {
        "fr" : "04 32 61 93 86"
      }
    }, {
      "identifiant" : 93587579,
      "type" : {
        "elementReferenceType" : "MoyenCommunicationType",
        "id" : 204
      },
      "coordonnees" : {
        "fr" : "ot-culture@mairiemaillane.fr"
      }
    } ]
  }, {
    "identifiant" : 19890317,
    "referent" : false,
    "civilite" : {
      "elementReferenceType" : "ContactCivilite",
      "id" : 443
    },
    "nom" : "TELLIER-MOURET",
    "prenom" : "Jean-Christophe",
    "fonction" : {
      "elementReferenceType" : "ContactFonction",
      "id" : 457
    }
  } ],
  "territoires" : [ {
    "type" : "TERRITOIRE",
    "id" : 591381
  }, {
    "type" : "TERRITOIRE",
    "id" : 591419
  }, {
    "type" : "TERRITOIRE",
    "id" : 658199
  }, {
    "type" : "TERRITOIRE",
    "id" : 4819487
  }, {
    "type" : "TERRITOIRE",
    "id" : 5127066
  }, {
    "type" : "TERRITOIRE",
    "id" : 5424410
  }, {
    "type" : "TERRITOIRE",
    "id" : 5447176
  } ],
  "informationsStructure" : { },
  "formatVersion" : "v002",
  "enquete" : { }
}